{
	"name": "white_special_ae_part",
	"plugin-id": "Sprite",
	"sid": 238756383551559,
	"isGlobal": false,
	"instanceVariables": [],
	"behaviorTypes": [],
	"effectTypes": [],
	"animations": {
		"items": [
			{
				"frames": [
					{
						"width": 85,
						"height": 324,
						"originX": 0.4823529411764706,
						"originY": 0.49691358024691357,
						"originalSource": "",
						"exportFormat": "lossless",
						"exportQuality": 0.8,
						"imageSpriteId": 946343,
						"collisionPoly": {
							"points": [
								0.09411764705882353,
								0.5185185185185185,
								0.4823529411764706,
								0.012345679012345678,
								0.8705882352941177,
								0.5154320987654321,
								0.8705882352941177,
								0.49691358024691357,
								0.8705882352941177,
								0.47530864197530864,
								0.4823529411764706,
								0.9845679012345679,
								0.08235294117647059,
								0.47530864197530864,
								0.08235294117647059,
								0.49691358024691357
							]
						},
						"useCollisionPoly": true,
						"duration": 1
					},
					{
						"width": 216,
						"height": 302,
						"originX": 1.1111111111111112,
						"originY": 0.5132450331125827,
						"originalSource": "",
						"exportFormat": "lossless",
						"exportQuality": 0.8,
						"imageSpriteId": 787867,
						"collisionPoly": {
							"points": [
								0.3425925925925926,
								0.09602649006622517,
								0.9722222222222222,
								0.7417218543046358,
								0.33796296296296297,
								0.5132450331125827,
								0.9490740740740741,
								0.26490066225165565,
								0.3101851851851852,
								0.9503311258278145,
								0.023148148148148147,
								0.5132450331125827
							]
						},
						"useCollisionPoly": true,
						"duration": 1
					},
					{
						"width": 211,
						"height": 74,
						"originX": -0.13744075829383887,
						"originY": 0.5405405405405406,
						"originalSource": "",
						"exportFormat": "lossless",
						"exportQuality": 0.8,
						"imageSpriteId": 9409463,
						"collisionPoly": {
							"points": [
								0.21800947867298578,
								0.05405405405405406,
								0.9715639810426541,
								0.5405405405405406,
								0.1943127962085308,
								0.9459459459459456,
								0.018957345971563982,
								0.5405405405405406
							]
						},
						"useCollisionPoly": true,
						"duration": 1
					},
					{
						"width": 212,
						"height": 125,
						"originX": -0.12735849056603774,
						"originY": 1.256,
						"originalSource": "",
						"exportFormat": "lossless",
						"exportQuality": 0.8,
						"imageSpriteId": 9859106,
						"useCollisionPoly": true,
						"duration": 1
					},
					{
						"width": 205,
						"height": 116,
						"originX": -0.15121951219512195,
						"originY": -0.31896551724137934,
						"originalSource": "",
						"exportFormat": "lossless",
						"exportQuality": 0.8,
						"imageSpriteId": 6590750,
						"useCollisionPoly": true,
						"duration": 1
					}
				],
				"sid": 614752897113435,
				"name": "Animation 1",
				"isLooping": false,
				"isPingPong": false,
				"repeatCount": 1,
				"repeatTo": 0,
				"speed": 0
			}
		],
		"subfolders": []
	}
}