{
	"name": "Capital_white_g",
	"plugin-id": "Sprite",
	"sid": 207207727766333,
	"isGlobal": false,
	"instanceVariables": [],
	"behaviorTypes": [],
	"effectTypes": [],
	"animations": {
		"items": [
			{
				"frames": [
					{
						"width": 335,
						"height": 433,
						"originX": 0.5,
						"originY": 0.5,
						"originalSource": "",
						"exportFormat": "lossless",
						"exportQuality": 0.8,
						"imageSpriteId": 7429573,
						"collisionPoly": {
							"points": [
								0.16417910447761194,
								0.12702078521939955,
								0.5,
								0,
								0.8417910447761194,
								0.12009237875288684,
								0.9970149253731343,
								0.5,
								0.835820895522388,
								0.8729792147806005,
								0.5,
								0.9976905311778291,
								0.14328358208955225,
								0.8868360277136259,
								0,
								0.5
							]
						},
						"useCollisionPoly": true,
						"imagePoints": [
							{
								"name": "Image Point 1",
								"x": 0.4746268656716418,
								"y": 0.03464203233256351
							},
							{
								"name": "Image Point 2",
								"x": 0.47761194029850745,
								"y": 0.9237875288683602
							}
						],
						"duration": 1
					}
				],
				"sid": 301730095639823,
				"name": "Animation 1",
				"isLooping": false,
				"isPingPong": false,
				"repeatCount": 1,
				"repeatTo": 0,
				"speed": 5
			}
		],
		"subfolders": []
	}
}